setup.py
distributions298342/Binomialdistribution.py
distributions298342/Gaussiandistribution.py
distributions298342/Generaldistribution.py
distributions298342/__init__.py
distributions298342.egg-info/PKG-INFO
distributions298342.egg-info/SOURCES.txt
distributions298342.egg-info/dependency_links.txt
distributions298342.egg-info/not-zip-safe
distributions298342.egg-info/top_level.txt