Metadata-Version: 1.0
Name: distributions298342
Version: 0.1
Summary: Gaussian distributions and Binomial distribution class
Home-page: UNKNOWN
Author: Sudeendra
Author-email: UNKNOWN
License: UNKNOWN
Platform: UNKNOWN
